yaqd_becker_hickl/VERSION
yaqd_becker_hickl/__init__.py
yaqd_becker_hickl/__version__.py
yaqd_becker_hickl/_becker_hickl_spc130.py
yaqd_becker_hickl/becker-hickl-spc130.avpr
yaqd_becker_hickl/becker-hickl-spc130.toml
yaqd_becker_hickl-2022.6.0.dist-info/entry_points.txt
yaqd_becker_hickl-2022.6.0.dist-info/LICENSE
yaqd_becker_hickl-2022.6.0.dist-info/WHEEL
yaqd_becker_hickl-2022.6.0.dist-info/METADATA
yaqd_becker_hickl-2022.6.0.dist-info/RECORD
